streamlit_image_comparison/__init__.py
streamlit_image_comparison-0.0.4.dist-info/LICENSE
streamlit_image_comparison-0.0.4.dist-info/METADATA
streamlit_image_comparison-0.0.4.dist-info/WHEEL
streamlit_image_comparison-0.0.4.dist-info/top_level.txt
streamlit_image_comparison-0.0.4.dist-info/RECORD
