Metadata-Version: 2.1
Name: streamlit-image-comparison
Version: 0.0.4
Summary: A Streamlit Component to compare images with a slider in Streamlit apps.
Home-page: https://github.com/fcakyon/streamlit-image-comparison
Author: fcakyon
License: MIT
Classifier: License :: OSI Approved :: MIT License
Classifier: Operating System :: OS Independent
Classifier: Intended Audience :: Developers
Classifier: Intended Audience :: Science/Research
Classifier: Programming Language :: Python :: 3
Classifier: Programming Language :: Python :: 3.7
Classifier: Programming Language :: Python :: 3.8
Classifier: Programming Language :: Python :: 3.9
Classifier: Programming Language :: Python :: 3.10
Classifier: Topic :: Software Development :: Libraries
Classifier: Topic :: Software Development :: Libraries :: Python Modules
Requires-Python: >=3.7
Provides-Extra: dev
License-File: LICENSE
